bbterm/__init__.py
bbterm/animation_test.py
bbterm/canvas.py
bbterm/errors.py
bbterm/font.py
bbterm/inline_font.py
bbterm/main.py
bbterm/protocol.py
bbterm/sprites.py
bbterm/telnet_client.py
bbterm/extensions/__init__.py
bbterm/extensions/ansi.py
bbterm/extensions/slash.py
bbterm-0.0.4.dist-info/METADATA
bbterm-0.0.4.dist-info/WHEEL
bbterm-0.0.4.dist-info/entry_points.txt
bbterm-0.0.4.dist-info/licenses/LICENSE
bbterm-0.0.4.dist-info/RECORD
